{
  "parent": "spectrum:midgame/brew_potion_in_potion_workshop",
  "display": {
    "icon": {
      "id": "spectrum:lesser_potion_pendant",
      "components": {
        "spectrum:ink_powered_potion_data": {
          "color": 14981690,
          "effects": [
            {
              "ink_color": "spectrum:red",
              "ink_cost": 4,
              "effect": {
                "id": "minecraft:absorption",
                "amplifier": 0,
                "duration": 3600
              }
            }
          ]
        }
      }
    },
    "title": {
      "translate": "advancements.spectrum.fill_potion_pendant.title"
    },
    "description": {
      "translate": "advancements.spectrum.fill_potion_pendant.description"
    }
  },
  "criteria": {
    "filled_potion_pendant": {
      "trigger": "spectrum:potion_workshop_brewing",
      "conditions": {
        "item": "#spectrum:potion_pendants",
        "effect_count": {
          "min": 1
        }
      }
    },
    "gotten_previous": {
      "trigger": "revelationary:advancement_gotten",
      "conditions": {
        "advancement_identifier": "spectrum:midgame/brew_potion_in_potion_workshop"
      }
    }
  }
}